cridis/__init__.py
cridis/httputil.py
cridis/provider/dmdata.py
cridis/provider/earlyest.py
cridis/provider/emsc.py
cridis/provider/gfz.py
cridis/provider/naver.py
cridis/provider/safekorea.py
cridis/provider/usgs.py
cridis/provider/kma/apihub.py
cridis/provider/kma/nuri.py
cridis/provider/kma/pews.py
cridis-0.0.1a0.dist-info/METADATA
cridis-0.0.1a0.dist-info/WHEEL
cridis-0.0.1a0.dist-info/RECORD
